<INDEX><ORDER>;</ORDER><JAVASCRIPTINLINE>;</JAVASCRIPTINLINE><SEE>semicolon</SEE></INDEX>
<INDEX><ORDER>;5</ORDER><JAVASCRIPTINLINE>=&gt;</JAVASCRIPTINLINE><SEEALSO>lambda expression</SEEALSO><FRAGILE/></INDEX>  
<INDEX><JAVASCRIPTINLINE>?</JAVASCRIPTINLINE><SPACE/><JAVASCRIPTINLINE>:</JAVASCRIPTINLINE><ORDER>?:</ORDER><SEEALSO>conditional expression</SEEALSO><FRAGILE/></INDEX>
<INDEX><ORDER>0p</ORDER>$\pi$<SEE>pi</SEE><FRAGILE/></INDEX>
<INDEX><ORDER>=</ORDER><JAVASCRIPTINLINE>=</JAVASCRIPTINLINE><SEEALSO>assignment</SEEALSO><FRAGILE/></INDEX>
<INDEX>abstract data<SEEALSO>data abstraction</SEEALSO><FRAGILE/></INDEX>
<INDEX>abstraction<SEEALSO>means of abstraction; data abstraction; higher-order functions</SEEALSO><FRAGILE/></INDEX>
<INDEX>agenda<SEE>digital-circuit simulation</SEE><FRAGILE/></INDEX>
<INDEX>algebra, symbolic<SEE>symbolic algebra</SEE><FRAGILE/></INDEX>
<INDEX><ORDER>amb eval</ORDER><JAVASCRIPTINLINE>amb</JAVASCRIPTINLINE> evaluator<SEE>nondeterministic evaluator</SEE><FRAGILE/></INDEX>
<INDEX>argument passing<SEE>call-by-name argument passing; call-by-need argument passing</SEE><FRAGILE/></INDEX>
<INDEX>arithmetic<SUBINDEX>generic</SUBINDEX><SEEALSO>generic arithmetic operations</SEEALSO><FRAGILE/></INDEX>
<INDEX>arithmetic<SUBINDEX>on polynomials</SUBINDEX><SEE>polynomial arithmetic</SEE><FRAGILE/></INDEX>
<INDEX>array<SEE>vector (data structure)</SEE><FRAGILE/></INDEX>
<INDEX>arrow function<SEE>lambda expression</SEE><FRAGILE/></INDEX>
<INDEX>assignment expression<SEE>assignment</SEE><FRAGILE/></INDEX>
<INDEX>automatic search<SEEALSO>search</SEEALSO><FRAGILE/></INDEX>
<INDEX>backtracking<SEEALSO>nondeterministic computing</SEEALSO><FRAGILE/></INDEX>
<INDEX>balanced binary tree<SEEALSO>binary tree</SEEALSO><FRAGILE/></INDEX>
<INDEX>binary numbers, addition of<SEE>adder</SEE><FRAGILE/></INDEX>
<INDEX><ORDER>break</ORDER><JAVASCRIPTINLINE>break</JAVASCRIPTINLINE> (keyword)<SEEALSO>while loop</SEEALSO><FRAGILE/></INDEX>
<INDEX>case analysis<SEEALSO>conditional expression</SEEALSO><FRAGILE/></INDEX>
<INDEX>changing money<SEE>counting change</SEE><FRAGILE/></INDEX>
<INDEX>circuit<SUBINDEX>digital</SUBINDEX><SEE>digital-circuit simulation</SEE><FRAGILE/></INDEX>
<INDEX>code<SUBINDEX>Huffman</SUBINDEX><SEE>Huffman code</SEE><FRAGILE/></INDEX>
<INDEX>combination<SEEALSO>operator combination; function application</SEEALSO><FRAGILE/></INDEX>	<INDEX>combination, means of<SEEALSO>closure</SEEALSO><FRAGILE/></INDEX>
<INDEX>compound expression<SEEALSO>operator combination; function application</SEEALSO><FRAGILE/></INDEX>
<INDEX>compilation<SEE>compiler</SEE><FRAGILE/></INDEX>
<INDEX>compiler for JavaScript<SUBINDEX>code generators</SUBINDEX><SEE><JAVASCRIPTINLINE>compile_</JAVASCRIPTINLINE><LATEXINLINE>$\ldots$</LATEXINLINE></SEE><FRAGILE/></INDEX>
<INDEX>compiler for JavaScript<SEEALSO>code generator; compile-time environment; instruction sequence; linkage descriptor; target register</SEEALSO><FRAGILE/></INDEX>
<INDEX>compound function<SEEALSO>function</SEEALSO><FRAGILE/></INDEX>
<INDEX>computational process<SEEALSO>process</SEEALSO><FRAGILE/></INDEX>
<INDEX>concatenation<SEE>string concatenation</SEE><FRAGILE/></INDEX>
<INDEX>conditional expression<SEEALSO>case analysis</SEEALSO><FRAGILE/></INDEX>
<INDEX><ORDER>const</ORDER><JAVASCRIPTINLINE>const</JAVASCRIPTINLINE> (keyword)<SEE>constant declaration</SEE><FRAGILE/></INDEX>
<INDEX>continuation<SUBINDEX>in nondeterministic evaluator</SUBINDEX><SEEALSO>failure continuation; success continuation</SEEALSO><FRAGILE/></INDEX>
<INDEX><ORDER>continue</ORDER><LATEXINLINE>\textbf{\texttt{continue}}</LATEXINLINE> (keyword)<SEEALSO>while loop</SEEALSO><FRAGILE/></INDEX>
<INDEX>controller for register machine<SEEALSO>register-machine language</SEEALSO><FRAGILE/></INDEX>
<INDEX>data<SUBINDEX>abstract</SUBINDEX><SEEALSO>data abstraction</SEEALSO><FRAGILE/></INDEX>
<INDEX>data<SUBINDEX>mutable</SUBINDEX><SEE>mutable data objects</SEE><FRAGILE/></INDEX>
<INDEX>data abstraction<SEEALSO>metacircular evaluator</SEEALSO><FRAGILE/></INDEX>
<INDEX>declaration<SEEALSO>internal declaration</SEEALSO><FRAGILE/></INDEX>
<INDEX>differential equation<SEEALSO><JAVASCRIPTINLINE>solve</JAVASCRIPTINLINE></SEEALSO><FRAGILE/></INDEX>
<INDEX>dispatching<SUBINDEX>on type</SUBINDEX><SEEALSO>data-directed programming</SEEALSO><FRAGILE/></INDEX>
<INDEX>efficiency<SEEALSO>order of growth</SEEALSO><FRAGILE/></INDEX>
<INDEX><ORDER>else</ORDER><JAVASCRIPTINLINE>else</JAVASCRIPTINLINE> (keyword)<SEEALSO>conditional statement</SEEALSO><FRAGILE/></INDEX>
<INDEX>empty list<SEEALSO><ORDER>null</ORDER><JAVASCRIPTINLINE>null</JAVASCRIPTINLINE></SEEALSO><FRAGILE/></INDEX>
<INDEX>environment<SUBINDEX>compile-time</SUBINDEX><SEE>compile-time environment</SEE><FRAGILE/></INDEX>
<INDEX>environment<SUBINDEX>global</SUBINDEX><SEE>global environment</SEE><FRAGILE/></INDEX>
<INDEX>environment<SUBINDEX>program</SUBINDEX><SEE>program environment</SEE><FRAGILE/></INDEX>
<INDEX>equation, solving<SEE>half-interval method; Newton's method; <JAVASCRIPTINLINE>solve</JAVASCRIPTINLINE></SEE><FRAGILE/></INDEX>
<INDEX>Euclid's Algorithm<SEEALSO>greatest common divisor</SEEALSO><FRAGILE/></INDEX>
<INDEX>evaluation<SUBINDEX>applicative-order</SUBINDEX><SEE>applicative-order evaluation</SEE><FRAGILE/></INDEX>
<INDEX>evaluation<SUBINDEX>normal-order</SUBINDEX><SEE>normal-order evaluation</SEE><FRAGILE/></INDEX>
<INDEX>evaluation<SUBINDEX>order of subexpression evaluation</SUBINDEX><SEE>order of evaluation</SEE><FRAGILE/></INDEX>
<INDEX>evaluation<SUBINDEX>delayed</SUBINDEX><SEE>delayed evaluation</SEE><FRAGILE/></INDEX>
<INDEX>evaluation<SUBINDEX>environment model of</SUBINDEX><SEE>environment model of evaluation</SEE><FRAGILE/></INDEX>
<INDEX>evaluation<SUBINDEX>substitution model of</SUBINDEX><SEE>substitution model of function application</SEE><FRAGILE/></INDEX>
<INDEX>evaluator<SEEALSO>interpreter</SEEALSO><FRAGILE/></INDEX>
<INDEX>evaluators<SEE>metacircular evaluator; analyzing evaluator; lazy evaluator; nondeterministic evaluator; query interpreter; explicit-control evaluator</SEE><FRAGILE/></INDEX>
<INDEX>expression<SUBINDEX>algebraic</SUBINDEX><SEE>algebraic expressions</SEE><FRAGILE/></INDEX>
<INDEX>expression<SEEALSO>compound expression; primitive expression</SEEALSO><FRAGILE/></INDEX>
<INDEX>expression<SUBINDEX>symbolic</SUBINDEX><SEEALSO>symbol(s)</SEEALSO><FRAGILE/></INDEX>
<INDEX>factorial<SEEALSO><JAVASCRIPTINLINE>factorial</JAVASCRIPTINLINE></SEEALSO><FRAGILE/></INDEX>
<INDEX>Fibonacci numbers<SEEALSO><JAVASCRIPTINLINE>fib</JAVASCRIPTINLINE></SEEALSO><FRAGILE/></INDEX>
<INDEX>Fibonacci numbers<SUBINDEX>infinite stream of</SUBINDEX><SEE><JAVASCRIPTINLINE>fibs</JAVASCRIPTINLINE></SEE><FRAGILE/></INDEX>
<INDEX><ORDER>for</ORDER><JAVASCRIPTINLINE>for</JAVASCRIPTINLINE> (keyword)<SEEALSO>for loop</SEEALSO><FRAGILE/></INDEX>
<INDEX>formal parameters<SEE>parameters</SEE><FRAGILE/></INDEX>
<INDEX>fraction<SEE>rational number(s)</SEE><FRAGILE/></INDEX>
<INDEX>frame (query interpreter)<SEEALSO>pattern matching; unification</SEEALSO><FRAGILE/></INDEX>
<INDEX><ORDER>function</ORDER><JAVASCRIPTINLINE>function</JAVASCRIPTINLINE> (keyword)<SEEALSO>function declaration</SEEALSO><FRAGILE/></INDEX>
<INDEX><FUNCTION/><SUBINDEX>higher-order</SUBINDEX><SEE>higher-order function</SEE><FRAGILE/></INDEX>
<INDEX>function application<SUBINDEX>substitution model of</SUBINDEX><SEE>substitution model of function application</SEE><FRAGILE/></INDEX>
<INDEX>GCD<SEE>greatest common divisor</SEE><FRAGILE/></INDEX>
<INDEX>graphics<SEE>picture language</SEE><FRAGILE/></INDEX>
<INDEX>greatest common divisor<SEEALSO><JAVASCRIPTINLINE>gcd</JAVASCRIPTINLINE></SEEALSO><FRAGILE/></INDEX>
<INDEX>hoisting<SEE>internal declaration; lexical scoping; scope of a name</SEE><FRAGILE/></INDEX>
<INDEX><ORDER>how to</ORDER>``how to'' vs.<SPACE/>``what is'' description<SEE>imperative vs.<SPACE/>declarative knowledge</SEE><FRAGILE/></INDEX>
<INDEX><ORDER>if</ORDER><JAVASCRIPTINLINE>if</JAVASCRIPTINLINE> (keyword)<SEEALSO>conditional statement</SEEALSO><FRAGILE/></INDEX>
<INDEX>infinite stream(s)<SUBINDEX>of integers</SUBINDEX><SEE><JAVASCRIPTINLINE>integers</JAVASCRIPTINLINE></SEE><FRAGILE/></INDEX>
<INDEX>infinite stream(s)<SUBINDEX>of Fibonacci numbers</SUBINDEX><SEE><JAVASCRIPTINLINE>fibs</JAVASCRIPTINLINE></SEE><FRAGILE/></INDEX>
<INDEX>infinite stream(s)<SUBINDEX>of prime numbers</SUBINDEX><SEE><JAVASCRIPTINLINE>primes</JAVASCRIPTINLINE></SEE><FRAGILE/></INDEX>
<INDEX>information retrieval<SEE>data base</SEE><FRAGILE/></INDEX>
<INDEX>integral<SEEALSO>definite integral; Monte Carlo integration</SEEALSO><FRAGILE/></INDEX>
<INDEX>interpreter<SEEALSO>evaluator</SEEALSO><FRAGILE/></INDEX>
<INDEX>iteration contructs<SEE>looping constructs</SEE><FRAGILE/></INDEX>
<INDEX>iterative process<SUBINDEX>implemented by function call</SUBINDEX><SEEALSO>tail recursion</SEEALSO><FRAGILE/></INDEX>
<INDEX>language<SEE>parsing natural language; programming language</SEE><FRAGILE/></INDEX>
<INDEX><ORDER>let</ORDER><JAVASCRIPTINLINE>let</JAVASCRIPTINLINE> (keyword)<SEEALSO>variable declaration</SEEALSO><FRAGILE/></INDEX>
<INDEX>lexical scoping<SEEALSO>scope of a name</SEEALSO><FRAGILE/></INDEX>
<INDEX>LIFO buffer<SEE>stack</SEE><FRAGILE/></INDEX>
<INDEX>list(s)<SUBINDEX>empty</SUBINDEX><SEE>empty list</SEE><FRAGILE/></INDEX>
<INDEX>logic programming<SEEALSO>query language; query interpreter</SEEALSO><FRAGILE/></INDEX>
<INDEX>looping constructs<SEEALSO>for loop; while loop</SEEALSO><FRAGILE/></INDEX>
<INDEX>magician<SEE>numerical analyst</SEE><FRAGILE/></INDEX> 
<INDEX>making change<SEE>counting change</SEE><FRAGILE/></INDEX>
<INDEX>mathematical function<SEE>function (mathematical)</SEE><FRAGILE/></INDEX>
<INDEX>means of combination<SEEALSO>closure</SEEALSO><FRAGILE/></INDEX>
<INDEX>merging infinite streams<SEE>infinite stream(s)</SEE><FRAGILE/></INDEX>
<INDEX>modified registers<SEE>instruction sequence</SEE><FRAGILE/></INDEX>
<INDEX>money, changing<SEE>counting change</SEE><FRAGILE/></INDEX>
<INDEX>mutable data objects<SEEALSO>queue; table</SEEALSO><FRAGILE/></INDEX>
<INDEX>name<SEEALSO>local name; constant; variable</SEEALSO><FRAGILE/></INDEX>
<INDEX>name<SUBINDEX>scope of</SUBINDEX><SEEALSO>scope of a name</SEEALSO><FRAGILE/></INDEX>
<INDEX>natural language parsing<SEE>parsing natural language</SEE><FRAGILE/></INDEX>
<INDEX>needed registers<SEE>instruction sequence</SEE><FRAGILE/></INDEX>
<INDEX>nested declaration(s)<SEE>internal declaration</SEE><FRAGILE/></INDEX>
<INDEX>nested mapping(s)<SEE>mapping</SEE><FRAGILE/></INDEX>
<INDEX>normal-order evaluator<SEE>lazy evaluator</SEE><FRAGILE/></INDEX>
<INDEX>operator precedence<SEE>precedence</SEE><FRAGILE/></INDEX>
<INDEX>order of subexpression evaluation<SEE>order of evaluation</SEE><FRAGILE/></INDEX>
<INDEX>parameter passing<SEE>call-by-name argument passing; call-by-need argument passing</SEE><FRAGILE/></INDEX>
<INDEX>prime number(s)<SUBINDEX>infinite stream of</SUBINDEX><SEE><JAVASCRIPTINLINE>primes</JAVASCRIPTINLINE></SEE><FRAGILE/></INDEX>
<INDEX>primitive query<SEE>simple query</SEE><FRAGILE/></INDEX>
<INDEX>program<SUBINDEX>structure of</SUBINDEX><SEEALSO>abstraction barriers</SEEALSO><FRAGILE/></INDEX>
<INDEX>programming<SUBINDEX>data-directed</SUBINDEX><SEE>data-directed programming</SEE><FRAGILE/></INDEX>
<INDEX>programming<SUBINDEX>functional</SUBINDEX><SEE>functional programming</SEE><FRAGILE/></INDEX>
<INDEX>query<SEEALSO>simple query; compound query</SEEALSO><FRAGILE/></INDEX>
<INDEX>query language<SUBINDEX>simple query</SUBINDEX><SEE>simple query</SEE><FRAGILE/></INDEX>
<INDEX>query language<SUBINDEX>compound query</SUBINDEX><SEE>compound query</SEE><FRAGILE/></INDEX>
<INDEX>query language<SUBINDEX>rule</SUBINDEX><SEE>rule</SEE><FRAGILE/></INDEX>
<INDEX>query interpreter<SUBINDEX>simple query</SUBINDEX><SEE>simple query</SEE><FRAGILE/></INDEX>
<INDEX>query interpreter<SUBINDEX>compound query</SUBINDEX><SEE>compound query</SEE><FRAGILE/></INDEX>
<INDEX>query interpreter<SUBINDEX>rule</SUBINDEX><SEE>rule</SEE><FRAGILE/></INDEX>
<INDEX>read-evaluate-print loop<SEEALSO>driver loop</SEEALSO><FRAGILE/></INDEX>
<INDEX><ORDER>return</ORDER><JAVASCRIPTINLINE>return</JAVASCRIPTINLINE> (keyword)<SEEALSO>return statement</SEEALSO><FRAGILE/></INDEX>
<!--
    <INDEX>recursion<SUBINDEX>infinite<SEE>infinite recursion</SEE></SUBINDEX></INDEX>
    <INDEX>infinite recursion<SEE>recursion, infinite</SEE></INDEX>
-->
<INDEX>roots of equation<SEE>half-interval method; Newton<APOS/>s method</SEE><FRAGILE/></INDEX>
<INDEX>scope of a name<SEEALSO>lexical scoping</SEEALSO><FRAGILE/></INDEX>
<INDEX>simulation<SUBINDEX>Monte Carlo</SUBINDEX><SEE>Monte Carlo simulation</SEE><FRAGILE/></INDEX>
<INDEX>simulation<SUBINDEX><ORDER>register</ORDER>of register machine</SUBINDEX><SEE>register-machine simulator</SEE><FRAGILE/></INDEX>
<INDEX>simulation<SUBINDEX><ORDER>digital</ORDER>of digital circuit</SUBINDEX><SEE>digital-circuit simulation</SEE><FRAGILE/></INDEX>
<INDEX>solving equation<SEE>half-interval method; Newton<APOS/>s method; <JAVASCRIPTINLINE>solve</JAVASCRIPTINLINE></SEE><FRAGILE/></INDEX>
<INDEX>square root<SEEALSO><JAVASCRIPTINLINE>sqrt</JAVASCRIPTINLINE></SEEALSO><FRAGILE/></INDEX>
<INDEX>state<SUBINDEX>local</SUBINDEX><SEE>local state</SEE><FRAGILE/></INDEX>
<INDEX>statement sequence<SEE>sequence of statements</SEE><FRAGILE/></INDEX>
<INDEX>stream(s)<SUBINDEX>infinite</SUBINDEX><SEE>infinite streams</SEE><FRAGILE/></INDEX>
<INDEX>string(s)<SUBINDEX>quotation marks for</SUBINDEX><SEE>quotation marks</SEE><FRAGILE/></INDEX>
<INDEX>symbolic expression<SEEALSO>string(s)</SEEALSO><FRAGILE/></INDEX>
<INDEX>synchronization<SEE>concurrency</SEE><FRAGILE/></INDEX>
<INDEX>syntax<SUBINDEX>abstract</SUBINDEX><SEE>abstract syntax</SEE><FRAGILE/></INDEX>
<INDEX>syntax<SEEALSO>syntactic form</SEEALSO><FRAGILE/></INDEX>
<INDEX>table<SUBINDEX>operation-and-type</SUBINDEX><SEE>operation-and-type table</SEE><FRAGILE/></INDEX>
<INDEX>temporal dead zone (TDZ)<SEE>declaration, use of name before</SEE><FRAGILE/></INDEX>
<INDEX>TDZ (temporal dead zone)<SEE>declaration, use of name before</SEE><FRAGILE/></INDEX>
<INDEX>ternary operator<SEE>conditional expression</SEE><FRAGILE/></INDEX>
<INDEX>tree<SUBINDEX>binary</SUBINDEX><SEEALSO>binary tree</SEEALSO><FRAGILE/></INDEX>
<INDEX><ORDER>what is</ORDER>``what is'' vs.<SPACE/>``how to'' description<SEE>declarative vs.<SPACE/>imperative knowledge</SEE><FRAGILE/></INDEX>
<INDEX><ORDER>while</ORDER><JAVASCRIPTINLINE>while</JAVASCRIPTINLINE> (keyword)<SEEALSO>while loop</SEEALSO><FRAGILE/></INDEX>
